{
    "cli": true,
    "target": "directory",
    "adapterName": "suedwind-ambientika",
    "title": "Südwind Ambientika Smart integration",
    "description": "Integration for Südwind Ambientika Smart decentral ventilation systems",
    "keywords": [
        "suedwind",
        "südwind",
        "ambientika",
        "decentral",
        "ventilation",
        "climate"
    ],
    "expert": "no",
    "features": [
        "adapter"
    ],
    "adminFeatures": [],
    "type": "climate-control",
    "startMode": "daemon",
    "connectionType": "cloud",
    "dataSource": "push",
    "connectionIndicator": "no",
    "language": "JavaScript",
    "nodeVersion": "20",
    "adminUi": "json",
    "tools": [
        "ESLint",
        "type checking"
    ],
    "eslintConfig": "official",
    "releaseScript": "no",
    "devServer": "no",
    "indentation": "Space (4)",
    "quotes": "single",
    "authorName": "baeri_wiliwonka",
    "authorGithub": "baeri_wiliwonka",
    "authorEmail": "soerenmilimonka@gmx.de",
    "gitRemoteProtocol": "HTTPS",
    "gitCommit": "no",
    "defaultBranch": "main",
    "license": "MIT License",
    "dependabot": "yes",
    "creatorVersion": "3.1.2"
}